Metadata-Version: 2.1
Name: frankenstein
Version: 1.0.2
Summary: Project Templates Brought to Life
Home-page: https://github.com/thespacedoctor/frankenstein
Author: David Young
Author-email: davidrobertyoung@gmail.com
License: MIT
Download-URL: https://github.com/thespacedoctor/frankenstein/archive/v1.0.2.zip
Keywords: templates
Platform: UNKNOWN
Classifier: Development Status :: 4 - Beta
Classifier: License :: OSI Approved :: MIT License
Classifier: Programming Language :: Python :: 3.7
Classifier: Topic :: Utilities
License-File: LICENSE
Requires-Dist: pyyaml
Requires-Dist: frankenstein
Requires-Dist: fundamentals
